video_matting/__init__.py
video_matting/__main__.py
video_matting/animegan.py
video_matting/camera.py
video_matting/create_model.py
video_matting/merge.py
video_matting/q.py
video_matting/rvm.py
video_matting/rvm_mobilenetv3_fp32.onnx
video_matting/video_matting_cli.py
video_matting-1.0.4.dist-info/LICENSE
video_matting-1.0.4.dist-info/METADATA
video_matting-1.0.4.dist-info/WHEEL
video_matting-1.0.4.dist-info/entry_points.txt
video_matting-1.0.4.dist-info/top_level.txt
video_matting-1.0.4.dist-info/RECORD
