Metadata-Version: 2.1
Name: video-matting
Version: 1.0.4
Summary: video tool
Home-page: https://github.com/CSPHQ/video-matting
Author: qhduan
Author-email: mail@qhduan.com
License: GPLv3
Keywords: pip,video
Platform: any
License-File: LICENSE
Requires-Dist: moviepy
Requires-Dist: tqdm
Requires-Dist: jax
Requires-Dist: jax[cpu]
Requires-Dist: onnxruntime
Requires-Dist: fire
Requires-Dist: numpy
Requires-Dist: opencv-python
